flaskoidc_azure/__init__.py
flaskoidc_azure/auth_azure.py
flaskoidc_azure/config.py
flaskoidc_azure-0.0.11.dist-info/LICENSE
flaskoidc_azure-0.0.11.dist-info/METADATA
flaskoidc_azure-0.0.11.dist-info/WHEEL
flaskoidc_azure-0.0.11.dist-info/top_level.txt
flaskoidc_azure-0.0.11.dist-info/RECORD
