Metadata-Version: 2.1
Name: flaskoidc-azure
Version: 0.0.11
Summary: Flask wrapper with pre-configured azure OIDC support
Home-page: https://github.com/kylg/flaskoidc_azure.git
Author: Jerry
Author-email: info@kylg.org
License: UNKNOWN
Platform: UNKNOWN
Requires-Python: >=3.6
Requires-Dist: FLASK
Requires-Dist: flask-sqlalchemy
Requires-Dist: flask-session
Requires-Dist: msal (<2,>=0.6.1)
